{
	"items": [
		{
			"id": "0",
			"name": "INVALID",
			"id_str": "item.INVALID",
			"tags": "",
			"image_path": "",
			"tier": "0",
			"max_stack": "0",
			"buy_price": "0",
			"sell_price": "0",
			"hold_offset": "0.0",
			"pickup_sound": "sound.grab",
			"drop_sound": "sound.grab"
		},
		{
			"id": "1",
			"id_str": "item.iron_pickaxe",
			"name": "Iron Pickaxe",
			"tags": "PICKAXE,TOOL,WEAPON",
			"image_path": "assets/images/items/Item_1.png",
			"tier": "0",
			"max_stack": "1",
			"buy_price": "0",
			"sell_price": "40",
			"attack_speed": "20",
			"attack_damage": "7",
			"knockback": "2",
			"crit_chance": "0.04",
			"world_override_image_path": "",
			"prefixes": "COMMON,UNIVERSAL",
			"pickaxe_power": "40.0",
			"pickup_sound": "sound.grab",
			"drop_sound": "sound.grab",
			"use_sound": "sound.swing",
			"hold_offset": "0.8"
		},
		{
			"id": "2",
			"id_str": "item.dirt_block",
			"name": "Dirt",
			"tags": "TILE,MATERIAL",
			"image_path": "assets/images/items/Item_2.png",
			"tier": "0",
			"max_stack": "999",
			"buy_price": "1",
			"sell_price": "0",
			"hold_offset": "0.0",
			"tile_id_str": "tile.dirt",
			"pickup_sound": "sound.grab",
			"drop_sound": "sound.grab"
		},
		{
			"id": "3",
			"id_str": "item.stone_block",
			"name": "Stone",
			"tags": "TILE,MATERIAL",
			"image_path": "assets/images/items/Item_3.png",
			"tier": "0",
			"max_stack": "999",
			"buy_price": "2",
			"sell_price": "0",
			"hold_offset": "0.0",
			"tile_id_str": "tile.stone",
			"pickup_sound": "sound.grab",
			"drop_sound": "sound.grab"
		},
		{
			"id": "4",
			"id_str": "item.iron_broadsword",
			"name": "Iron Broadsword",
			"tags": "LONGSWORD,WEAPON",
			"image_path": "assets/images/items/Item_4.png",
			"tier": "0",
			"max_stack": "1",
			"buy_price": "200",
			"sell_price": "20",
			"attack_speed": "20",
			"attack_damage": "12",
			"knockback": "5.5",
			"crit_chance": "0.04",
			"world_override_image_path": "",
			"prefixes": "COMMON,LONGSWORD,UNIVERSAL",
			"pickup_sound": "sound.grab",
			"drop_sound": "sound.grab",
			"use_sound": "sound.swing",
			"hold_offset": "0.8"
		},
		{
			"id": "5",
			"id_str": "item.mushroom",
			"name": "Mushroom",
			"tags": "TILE,MATERIAL",
			"image_path": "assets/images/items/Item_5.png",
			"tier": "0",
			"max_stack": "999",
			"buy_price": "5",
			"sell_price": "1",
			"tile_id_str": "tile.mushroom",
			"pickup_sound": "sound.grab",
			"drop_sound": "sound.grab",
			"hold_offset": "0.0"
		},
		{
			"id": "6",
			"id_str": "item.iron_ore",
			"name": "Iron Ore",
			"tags": "TILE,MATERIAL",
			"image_path": "assets/images/items/Item_11.png",
			"tier": "0",
			"max_stack": "999",
			"buy_price": "20",
			"sell_price": "10",
			"tile_id_str": "tile.pot_thick_brown",
			"pickup_sound": "sound.grab",
			"drop_sound": "sound.grab",
			"hold_offset": "0.0"
		},
		{
			"id": "7",
			"id_str": "item.dirt_wall",
			"name": "Dirt Wall",
			"tags": "WALL",
			"image_path": "assets/images/items/Item_30.png",
			"tier": "0",
			"max_stack": "999",
			"buy_price": "2",
			"sell_price": "0",
			"hold_offset": "0.0",
			"pickup_sound": "sound.grab",
			"drop_sound": "sound.grab",
			"wall_id_str": "wall.dirt"
		},
		{
			"id": "8",
			"id_str": "item.stone_wall",
			"name": "Stone Wall",
			"tags": "WALL",
			"image_path": "assets/images/items/Item_26.png",
			"tier": "0",
			"max_stack": "999",
			"buy_price": "2",
			"sell_price": "0",
			"hold_offset": "0.0",
			"pickup_sound": "sound.grab",
			"drop_sound": "sound.grab",
			"wall_id_str": "wall.stone"
		},
		{
			"id": "9",
			"id_str": "item.snow",
			"name": "Snow",
			"tags": "TILE",
			"image_path": "assets/images/items/Item_593.png",
			"tier": "0",
			"max_stack": "999",
			"buy_price": "5",
			"sell_price": "2",
			"tile_id_str": "tile.snow",
			"pickup_sound": "sound.grab",
			"drop_sound": "sound.grab",
			"hold_offset": "0.0"
		},
		{
			"id": "10",
			"id_str": "item.snow_wall",
			"name": "Snow Wall",
			"tags": "WALL",
			"image_path": "assets/images/items/Item_4489.png",
			"tier": "0",
			"max_stack": "999",
			"buy_price": "2",
			"sell_price": "0",
			"pickup_sound": "sound.grab",
			"drop_sound": "sound.grab",
			"hold_offset": "0.0",
			"wall_id_str": "wall.snow"
		},
		{
			"id": "11",
			"id_str": "item.ice",
			"name": "Ice",
			"tags": "TILE",
			"image_path": "assets/images/Items/item_664.png",
			"tier": "0",
			"max_stack": "999",
			"buy_price": "5",
			"sell_price": "0",
			"tile_id_str": "tile.none",
			"pickup_sound": "sound.grab",
			"drop_sound": "sound.grab",
			"hold_offset": "0.0"
		},
		{
			"id": "12",
			"id_str": "item.ice_wall",
			"name": "Ice Wall",
			"tags": "WALL",
			"image_path": "assets/images/items/Item_4506.png",
			"tier": "0",
			"max_stack": "999",
			"buy_price": "2",
			"sell_price": "5",
			"pickup_sound": "sound.grab",
			"drop_sound": "sound.grab",
			"hold_offset": "0.0",
			"wall_id_str": "wall.ice"
		},
		{
			"id": "13",
			"id_str": "item.wood",
			"name": "Wood",
			"tags": "TILE,MATERIAL",
			"image_path": "assets/images/items/Item_9.png",
			"tier": "0",
			"max_stack": "999",
			"buy_price": "5",
			"sell_price": "1",
			"tile_id_str": "tile.wood",
			"pickup_sound": "sound.grab",
			"drop_sound": "sound.grab",
			"hold_offset": "0.0"
		},
		{
			"id": "14",
			"id_str": "item.wood_wall",
			"name": "Wood Wall",
			"tier": "0",
			"max_stack": "999",
			"buy_price": "2",
			"sell_price": "0",
			"tags": "WALL",
			"image_path": "assets/images/items/item_93.png",
			"pickup_sound": "sound.grab",
			"drop_sound": "sound.grab",
			"wall_id_str": "wall.wood",
			"hold_offset": "0.0"
		},
		{
			"id": "15",
			"id_str": "item.copper_ore",
			"name": "Copper Ore",
			"tags": "TILE,MATERIAL",
			"image_path": "assets/images/items/Item_12.png",
			"tier": "0",
			"max_stack": "999",
			"buy_price": "10",
			"sell_price": "5",
			"tile_id_str": "tile.copper",
			"pickup_sound": "sound.grab",
			"drop_sound": "sound.grab",
			"hold_offset": "0.0"
		},
		{
			"id": "16",
			"id_str": "item.silver_ore",
			"name": "Silver Ore",
			"tags": "TILE,MATERIAL",
			"image_path": "assets/images/items/Item_14.png",
			"tier": "0",
			"max_stack": "999",
			"buy_price": "20",
			"sell_price": "10",
			"tile_id_str": "tile.pot_thick_brown",
			"pickup_sound": "sound.grab",
			"drop_sound": "sound.grab",
			"hold_offset": "0.0"
		},
		{
			"id": "17",
			"id_str": "item.sand",
			"name": "Sand",
			"tags": "MATERIAL,TILE",
			"image_path": "assets/images/items/item_169.png",
			"tier": "0",
			"max_stack": "999",
			"buy_price": "10",
			"sell_price": "0",
			"pickup_sound": "sound.grab",
			"drop_sound": "sound.grab",
			"hold_offset": "0.0",
			"tile_id_str": "tile.sand"
		},
		{
			"id": "18",
			"id_str": "item.hardened_sand_wall",
			"name": "Hardened Sand Wall",
			"tags": "WALL",
			"image_path": "assets/images/items/Item_3340.png",
			"tier": "0",
			"max_stack": "999",
			"buy_price": "10",
			"sell_price": "0",
			"pickup_sound": "sound.grab",
			"drop_sound": "sound.grab",
			"hold_offset": "0.0",
			"wall_id_str": "wall.hardened_sand"
		},
		{
			"id": "19",
			"id_str": "item.sandstone",
			"name": "Sandstone",
			"tags": "TILE,MATERIAL",
			"image_path": "assets/images/items/Item_3271.png",
			"tier": "0",
			"max_stack": "999",
			"buy_price": "5",
			"sell_price": "0",
			"tile_id_str": "tile.sandstone",
			"pickup_sound": "sound.grab",
			"drop_sound": "sound.grab",
			"hold_offset": "0.0"
		},
		{
			"id": "20",
			"id_str": "item.sandstone_wall",
			"name": "Sandstone Wall",
			"tags": "WALL",
			"image_path": "assets/images/items/Item_3273.png",
			"tier": "0",
			"max_stack": "999",
			"buy_price": "5",
			"sell_price": "0",
			"pickup_sound": "sound.grab",
			"drop_sound": "sound.grab",
			"hold_offset": "0.0",
			"wall_id_str": "wall.sandstone"
		},
		{
			"id": "21",
			"id_str": "item.wood_platform",
			"name": "Wood Platform",
			"tags": "TILE",
			"image_path": "assets/images/items/Item_94.png",
			"tier": "0",
			"max_stack": "999",
			"buy_price": "20",
			"sell_price": "5",
			"tile_id_str": "tile.platform_wood",
			"pickup_sound": "sound.grab",
			"drop_sound": "sound.grab",
			"hold_offset": "0.0"
		},
		{
			"id": "22",
			"id_str": "item.copper_broadsword",
			"name": "Copper Broadsword",
			"tags": "LONGSWORD,WEAPON",
			"image_path": "assets/images/items/Item_3508.png",
			"tier": "0",
			"max_stack": "1",
			"buy_price": "200",
			"sell_price": "20",
			"attack_speed": "45",
			"attack_damage": "5",
			"knockback": "10",
			"crit_chance": "0.03",
			"world_override_image_path": "",
			"prefixes": "COMMON,LONGSWORD,UNIVERSAL",
			"pickup_sound": "sound.grab",
			"drop_sound": "sound.grab",
			"use_sound": "sound.swing",
			"hold_offset": "0.8"
		},
		{
			"id": "23",
			"id_str": "item.excalibur",
			"name": "Excalibur",
			"tags": "LONGSWORD,WEAPON",
			"image_path": "assets/images/items/Item_368.png",
			"tier": "10",
			"max_stack": "1",
			"buy_price": "100000000",
			"sell_price": "20000000",
			"attack_speed": "35",
			"attack_damage": "1337",
			"knockback": "0",
			"crit_chance": "0.0",
			"world_override_image_path": "",
			"prefixes": "COMMON,LONGSWORD,UNIVERSAL",
			"pickup_sound": "sound.grab",
			"drop_sound": "sound.grab",
			"use_sound": "sound.swing",
			"hold_offset": "0.9"
		},
		{
			"id": "24",
			"id_str": "item.wood_broadsword",
			"name": "Wooden Sword",
			"tags": "LONGSWORD,WEAPON",
			"image_path": "assets/images/items/Item_24.png",
			"tier": "0",
			"max_stack": "1",
			"buy_price": "100",
			"sell_price": "10",
			"attack_speed": "50",
			"attack_damage": "3",
			"knockback": "6",
			"crit_chance": "0.03",
			"world_override_image_path": "",
			"prefixes": "COMMON,LONGSWORD,UNIVERSAL",
			"pickup_sound": "sound.grab",
			"drop_sound": "sound.grab",
			"use_sound": "sound.swing",
			"hold_offset": "0.8"
		},
		{
			"id": "25",
			"id_str": "item.wood_bow",
			"name": "Wooden Bow",
			"tags": "RANGED,WEAPON,bow",
			"image_path": "assets/images/items/Item_39.png",
			"tier": "0",
			"max_stack": "1",
			"buy_price": "150",
			"sell_price": "20",
			"attack_speed": "50",
			"attack_damage": "4",
			"knockback": "2",
			"crit_chance": "0.03",
			"world_override_image_path": "",
			"prefixes": "COMMON,RANGED,UNIVERSAL",
			"ranged_projectile_id_str": "projectile.arrow",
			"ranged_ammo_type": "arrow",
			"ranged_projectile_speed": "75.0",
			"ranged_accuracy": "0.9",
			"ranged_num_projectiles": "1",
			"pickup_sound": "sound.grab",
			"drop_sound": "sound.grab",
			"use_sound": "sound.bow",
			"hold_offset": "0.8"
		},
		{
			"id": "26",
			"id_str": "item.wooden_arrow",
			"name": "Wooden Arrow",
			"tags": "MATERIAL,AMMO",
			"image_path": "assets/images/items/Item_40.png",
			"tier": "0",
			"max_stack": "999",
			"buy_price": "5",
			"sell_price": "1",
			"ammo_type": "arrow",
			"ammo_damage": "4.0",
			"ammo_drag": "0.05",
			"ammo_gravity_mod": "1.2",
			"ammo_knockback_mod": "0",
			"pickup_sound": "sound.grab",
			"drop_sound": "sound.grab",
			"hold_offset": "0.0"
		},
		{
			"id": "27",
			"id_str": "item.musket",
			"name": "Musket",
			"tags": "RANGED,WEAPON,gun",
			"image_path": "assets/images/items/Item_96.png",
			"tier": "1",
			"max_stack": "1",
			"buy_price": "5000",
			"sell_price": "250",
			"attack_speed": "75",
			"attack_damage": "12",
			"knockback": "4",
			"crit_chance": "0.03",
			"world_override_image_path": "",
			"prefixes": "COMMON,RANGED,UNIVERSAL",
			"ranged_projectile_id_str": "projectile.bullet",
			"ranged_ammo_type": "bullet",
			"ranged_projectile_speed": "100.0",
			"ranged_accuracy": "0.95",
			"ranged_num_projectiles": "1",
			"pickup_sound": "sound.grab",
			"drop_sound": "sound.grab",
			"use_sound": "sound.gun_shot",
			"hold_offset": "0.0"
		},
		{
			"id": "28",
			"id_str": "item.musket_ball",
			"name": "Musket Ball",
			"tags": "MATERIAL,AMMO",
			"image_path": "assets/images/items/Item_97.png",
			"tier": "0",
			"max_stack": "999",
			"buy_price": "7",
			"sell_price": "1",
			"ammo_type": "bullet",
			"ammo_damage": "7.0",
			"ammo_drag": "0.05",
			"ammo_gravity_mod": "0.5",
			"ammo_knockback_mod": "0",
			"pickup_sound": "sound.grab",
			"drop_sound": "sound.grab",
			"hold_offset": "0.0"
		},
		{
			"id": "29",
			"id_str": "item.copper_coin",
			"name": "Copper Coin",
			"tags": "AMMO,coin",
			"image_path": "assets/images/items/Item_71.png",
			"tier": "0",
			"max_stack": "100",
			"buy_price": "0",
			"sell_price": "0",
			"ammo_type": "bullet",
			"ammo_damage": "2.0",
			"ammo_drag": "5.0",
			"ammo_gravity_mod": "1.0",
			"ammo_knockback_mod": "0",
			"pickup_sound": "sound.coins",
			"drop_sound": "sound.coins",
			"hold_offset": "0.0"
		},
		{
			"id": "30",
			"id_str": "item.silver_coin",
			"name": "Silver Coin",
			"tags": "AMMO,coin",
			"image_path": "assets/images/items/Item_72.png",
			"tier": "0",
			"max_stack": "100",
			"buy_price": "0",
			"sell_price": "0",
			"ammo_type": "bullet",
			"ammo_damage": "5.0",
			"ammo_drag": "2.5",
			"ammo_gravity_mod": "0.75",
			"ammo_knockback_mod": "0",
			"pickup_sound": "sound.coins",
			"drop_sound": "sound.coins",
			"hold_offset": "0.0"
		},
		{
			"id": "31",
			"id_str": "item.gold_coin",
			"name": "Gold Coin",
			"tags": "AMMO,coin",
			"image_path": "assets/images/items/Item_73.png",
			"tier": "0",
			"max_stack": "100",
			"buy_price": "0",
			"sell_price": "0",
			"ammo_type": "bullet",
			"ammo_damage": "50.0",
			"ammo_drag": "1.25",
			"ammo_gravity_mod": "0.5",
			"ammo_knockback_mod": "0",
			"pickup_sound": "sound.coins",
			"drop_sound": "sound.coins",
			"hold_offset": "0.0"
		},
		{
			"id": "32",
			"id_str": "item.platinum_coin",
			"name": "Platinum Coin",
			"tags": "AMMO,coin",
			"image_path": "assets/images/items/Item_74.png",
			"tier": "0",
			"max_stack": "999",
			"buy_price": "0",
			"sell_price": "0",
			"ammo_type": "bullet",
			"ammo_damage": "100.0",
			"ammo_drag": "0.625",
			"ammo_gravity_mod": "0.25",
			"ammo_knockback_mod": "0",
			"pickup_sound": "sound.coins",
			"drop_sound": "sound.coins",
			"hold_offset": "0.0"
		},
		{
			"id": "33",
			"id_str": "item.copper_pickaxe",
			"name": "Copper Pickaxe",
			"tags": "PICKAXE,TOOL,WEAPON",
			"image_path": "assets/images/items/Item_3509.png",
			"tier": "0",
			"max_stack": "1",
			"buy_price": "150",
			"sell_price": "10",
			"attack_speed": "50",
			"attack_damage": "2",
			"knockback": "10",
			"crit_chance": "0.03",
			"world_override_image_path": "",
			"prefixes": "COMMON,UNIVERSAL",
			"pickaxe_power": "35.0",
			"pickup_sound": "sound.grab",
			"drop_sound": "sound.grab",
			"use_sound": "sound.swing",
			"hold_offset": "0.8"
		},
		{
			"id": "34",
			"id_str": "item.copper_hammer",
			"name": "Copper Hammer",
			"tags": "hammer,TOOL,WEAPON",
			"image_path": "assets/images/items/Item_3505.png",
			"tier": "0",
			"max_stack": "1",
			"buy_price": "150",
			"sell_price": "10",
			"attack_speed": "50",
			"attack_damage": "2",
			"knockback": "10",
			"crit_chance": "0.03",
			"world_override_image_path": "",
			"prefixes": "COMMON,UNIVERSAL",
			"pickup_sound": "sound.grab",
			"drop_sound": "sound.grab",
			"use_sound": "sound.swing",
			"hammer_power": "0",
			"hold_offset": "0.8"
		},
		{
			"id": "35",
			"id_str": "item.wood_hammer",
			"name": "Wood Hammer",
			"tags": "hammer,TOOL,WEAPON",
			"image_path": "assets/images/items/Item_196.png",
			"tier": "0",
			"max_stack": "1",
			"buy_price": "150",
			"sell_price": "10",
			"attack_speed": "35",
			"attack_damage": "2",
			"knockback": "10",
			"crit_chance": "0.03",
			"world_override_image_path": "",
			"prefixes": "COMMON,UNIVERSAL",
			"pickup_sound": "sound.grab",
			"drop_sound": "sound.grab",
			"use_sound": "sound.swing",
			"hammer_power": "0",
			"hold_offset": "0.8"
		},
		{
			"id": "36",
			"id_str": "item.gel",
			"name": "Blue Gel",
			"tags": "MATERIAL",
			"image_path": "assets/images/items/Item_23.png",
			"tier": "0",
			"max_stack": "999",
			"buy_price": "5",
			"sell_price": "1",
			"pickup_sound": "sound.grab",
			"drop_sound": "sound.grab",
			"hold_offset": "0.0"
		},
		{
			"id": "37",
			"id_str": "item.wood_chest",
			"name": "Wooden Chest",
			"tags": "TILE",
			"image_path": "assets/images/items/Item_48.png",
			"tier": "0",
			"max_stack": "99",
			"buy_price": "50",
			"sell_price": "5",
			"tile_id_str": "tile.chest_wood",
			"pickup_sound": "sound.grab",
			"drop_sound": "sound.grab",
			"hold_offset": "0.0"
		},
		{
			"id": "38",
			"id_str": "item.workbench",
			"name": "Workbench",
			"tags": "TILE",
			"image_path": "assets/images/items/Item_36.png",
			"tier": "0",
			"max_stack": "99",
			"buy_price": "50",
			"sell_price": "5",
			"tile_id_str": "tile.crafting_table_wood",
			"pickup_sound": "sound.grab",
			"drop_sound": "sound.grab",
			"hold_offset": "0.0"
		},
		{
			"id": "39",
			"id_str": "item.wood_door",
			"name": "Wooden Door",
			"tags": "TILE",
			"image_path": "assets/images/items/Item_25.png",
			"tier": "0",
			"max_stack": "99",
			"buy_price": "50",
			"sell_price": "5",
			"tile_id_str": "tile.door_wood_closed",
			"pickup_sound": "sound.grab",
			"drop_sound": "sound.grab",
			"hold_offset": "0.0"
		},
		{
			"id": "40",
			"id_str": "item.torch",
			"name": "Torch",
			"tags": "TILE",
			"image_path": "assets/images/items/Item_8.png",
			"tier": "0",
			"max_stack": "999",
			"buy_price": "20",
			"sell_price": "2",
			"tile_id_str": "tile.torch",
			"pickup_sound": "sound.grab",
			"drop_sound": "sound.grab",
			"hold_offset": "0.0"
		},
		{
			"id": "41",
			"id_str": "item.spike",
			"name": "Spike",
			"tags": "TILE",
			"image_path": "assets/images/items/Item_147.png",
			"tier": "0",
			"max_stack": "999",
			"buy_price": "15",
			"sell_price": "0",
			"tile_id_str": "tile.spike",
			"pickup_sound": "sound.grab",
			"drop_sound": "sound.grab",
			"hold_offset": "0.0"
		},
		{
			"id": "42",
			"id_str": "item.grappling_hook",
			"name": "Grappling Hook",
			"tags": "GRAPPLE,TOOL",
			"image_path": "assets/images/items/grappling_hook.png",
			"tier": "0",
			"max_stack": "1",
			"buy_price": "10000",
			"sell_price": "500",
			"grapple_speed": "10.0",
			"grapple_chain_length": "100.0",
			"grapple_max_chains": "1",
			"grapple_chain_image_path": "assets/images/items/grappling_hook_chain.png",
			"grapple_claw_image_path": "assets/images/items/grappling_hook_claw.png",
			"pickup_sound": "sound.grab",
			"drop_sound": "sound.grab",
			"hold_offset": "0.0"
		},
		{
			"id": "43",
			"id_str": "item.water_bolt_spell",
			"name": "Water Bolt",
			"tier": "3",
			"max_stack": "999",
			"buy_price": "10000",
			"sell_price": "750",
			"tags": "MAGICAL,WEAPON",
			"image_path": "assets/images/items/Item_165.png",
			"pickup_sound": "sound.grab",
			"drop_sound": "sound.grab",
			"prefixes": "",
			"attack_speed": "12",
			"attack_damage": "5",
			"knockback": "0",
			"crit_chance": "0.03",
			"hold_offset": "0.0",
			"world_override_image_path": "",
			"use_sound": "sound.swing",
			"mana_cost": "20"
		},
		{
			"id": "44",
			"id_str": "item.painting_a",
			"name": "Painting A",
			"tier": "3",
			"max_stack": "999",
			"buy_price": "1000",
			"sell_price": "100",
			"hold_offset": "0",
			"tags": "TILE",
			"image_path": "assets/images/items/painting_a.png",
			"pickup_sound": "sound.grab",
			"drop_sound": "sound.grab",
			"tile_id_str": "tile.painting_a"
		},
		{
			"id": "45",
			"id_str": "item.painting_b",
			"name": "Painting B",
			"tier": "3",
			"max_stack": "999",
			"buy_price": "1000",
			"sell_price": "100",
			"hold_offset": "0",
			"tags": "TILE",
			"image_path": "assets/images/items/painting_b.png",
			"pickup_sound": "sound.grab",
			"drop_sound": "sound.grab",
			"tile_id_str": "tile.painting_b"
		},
		{
			"id": "46",
			"id_str": "item.painting_c",
			"name": "Painting C",
			"tier": "3",
			"max_stack": "999",
			"buy_price": "1000",
			"sell_price": "100",
			"hold_offset": "0",
			"tags": "TILE",
			"image_path": "assets/images/items/painting_c.png",
			"pickup_sound": "sound.grab",
			"drop_sound": "sound.grab",
			"tile_id_str": "tile.painting_c"
		},
		{
			"id": "47",
			"id_str": "item.copper_axe",
			"name": "Copper Axe",
			"tags": "AXE,TOOL,WEAPON",
			"image_path": "assets/images/items/Item_3506.png",
			"tier": "0",
			"max_stack": "1",
			"buy_price": "150",
			"sell_price": "10",
			"attack_speed": "50",
			"attack_damage": "2",
			"knockback": "10",
			"crit_chance": "0.03",
			"world_override_image_path": "",
			"prefixes": "COMMON,UNIVERSAL",
			"axe_power": "55.0",
			"pickup_sound": "sound.grab",
			"drop_sound": "sound.grab",
			"use_sound": "sound.swing",
			"hold_offset": "0.8"
		},
		{
			"id": "48",
			"id_str": "item.iron_shortsword",
			"name": "Iron Shortsword",
			"tags": "SHORTSWORD,WEAPON",
			"image_path": "assets/images/items/Item_6.png",
			"tier": "0",
			"max_stack": "1",
			"buy_price": "200",
			"sell_price": "20",
			"attack_speed": "20",
			"attack_damage": "12",
			"knockback": "5.5",
			"crit_chance": "0.04",
			"world_override_image_path": "",
			"prefixes": "COMMON,SHORTSWORD,UNIVERSAL",
			"pickup_sound": "sound.grab",
			"drop_sound": "sound.grab",
			"use_sound": "sound.swing",
			"hold_offset": "0.8"
		}
	]
}